CHANGELOG.rst
LICENSE
MANIFEST.in
README.rst
setup.py
parsely/__init__.py
parsely/database.py
parsely/resource.py
parsely/retry.py
parsely.egg-info/PKG-INFO
parsely.egg-info/SOURCES.txt
parsely.egg-info/dependency_links.txt
parsely.egg-info/requires.txt
parsely.egg-info/top_level.txt
parsely/resources/base.html
parsely/resources/enqueue.html
parsely/resources/parsely.css
parsely/resources/parsely.js
parsely/resources/task_list.html
parsely/resources/migrations/0.2.0.sql